zetamarkets_py/__init__.py
zetamarkets_py/client.py
zetamarkets_py/constants.py
zetamarkets_py/events.py
zetamarkets_py/exchange.py
zetamarkets_py/idl/zeta.json
zetamarkets_py/market.py
zetamarkets_py/orderbook.py
zetamarkets_py/pda.py
zetamarkets_py/risk.py
zetamarkets_py/serum_client/__init__.py
zetamarkets_py/serum_client/accounts/__init__.py
zetamarkets_py/serum_client/accounts/market_state.py
zetamarkets_py/serum_client/accounts/open_orders.py
zetamarkets_py/serum_client/accounts/orderbook.py
zetamarkets_py/serum_client/accounts/queue.py
zetamarkets_py/serum_client/program_id.py
zetamarkets_py/serum_client/types/__init__.py
zetamarkets_py/serum_client/types/account_flags.py
zetamarkets_py/serum_client/types/queue.py
zetamarkets_py/serum_client/types/slab.py
zetamarkets_py/solana_client/accounts/clock.py
zetamarkets_py/types.py
zetamarkets_py/utils.py
zetamarkets_py/zeta_client/README.md
zetamarkets_py/zeta_client/__init__.py
zetamarkets_py/zeta_client/accounts/__init__.py
zetamarkets_py/zeta_client/accounts/cross_margin_account.py
zetamarkets_py/zeta_client/accounts/cross_margin_account_manager.py
zetamarkets_py/zeta_client/accounts/cross_open_orders_map.py
zetamarkets_py/zeta_client/accounts/greeks.py
zetamarkets_py/zeta_client/accounts/insurance_deposit_account.py
zetamarkets_py/zeta_client/accounts/margin_account.py
zetamarkets_py/zeta_client/accounts/market_indexes.py
zetamarkets_py/zeta_client/accounts/market_node.py
zetamarkets_py/zeta_client/accounts/open_orders_map.py
zetamarkets_py/zeta_client/accounts/perp_sync_queue.py
zetamarkets_py/zeta_client/accounts/pricing.py
zetamarkets_py/zeta_client/accounts/referral_account.py
zetamarkets_py/zeta_client/accounts/referrer_account.py
zetamarkets_py/zeta_client/accounts/referrer_alias.py
zetamarkets_py/zeta_client/accounts/referrer_id_account.py
zetamarkets_py/zeta_client/accounts/referrer_pubkey_account.py
zetamarkets_py/zeta_client/accounts/settlement_account.py
zetamarkets_py-0.2.79.dist-info/LICENSE
zetamarkets_py-0.2.79.dist-info/METADATA
zetamarkets_py-0.2.79.dist-info/WHEEL
zetamarkets_py-0.2.79.dist-info/RECORD
