Metadata-Version: 2.3
Name: zetamarkets_py
Version: 0.2.79
Summary: Python SDK for Zeta Markets
License: Apache-2.0
Author: Tristan0x
Author-email: tristan@sierra.team
Requires-Python: >=3.10,<3.13
Classifier: License :: OSI Approved :: Apache Software License
Classifier: Programming Language :: Python :: 3
Classifier: Programming Language :: Python :: 3.10
Classifier: Programming Language :: Python :: 3.11
Classifier: Programming Language :: Python :: 3.12
Requires-Dist: anchorpy (>=0.20.1,<0.21.0)
Requires-Dist: colorlog (>=6.7.0,<7.0.0)
Requires-Dist: deprecated (>=1.2.14,<2.0.0)
Requires-Dist: jito_searcher_client (>=0.1.5,<0.2.0)
Requires-Dist: jsonrpcclient (>=4.0.3,<5.0.0)
Requires-Dist: solana (>=0.34.0,<0.35.0)
Requires-Dist: solders (>=0.21.0,<0.22.0)
Project-URL: Repository, https://github.com/zetamarkets/zetamarkets-py
